<?xml version="1.0" encoding="utf-8"?>
<!DOCTYPE hibernate-mapping PUBLIC "-//Hibernate/Hibernate Mapping DTD 3.0//EN"
"http://www.hibernate.org/dtd/hibernate-mapping-3.0.dtd">
<!-- 
    Mapping file autogenerated by MyEclipse Persistence Tools
-->
<hibernate-mapping>
    <class name="com.footmark.model.Review" table="review_table" catalog="footmarkdb" dynamic-insert="true">
        <id name="revid" type="java.lang.Long">
            <column name="revid" />
            <generator class="increment"></generator>
        </id>
        <many-to-one name="userByTouser" class="com.footmark.model.User" fetch="select" lazy="false" >
            <column name="touser" length="50" not-null="true" />
        </many-to-one>
        <many-to-one name="message" class="com.footmark.model.Message" fetch="select"  lazy="false">
            <column name="msgid" not-null="true" />
        </many-to-one>
        <many-to-one name="userByFromuser" class="com.footmark.model.User" fetch="select" lazy="false" >
            <column name="fromuser" length="50" not-null="true" />
        </many-to-one>
        <property name="revtime" type="java.sql.Timestamp">
            <column name="revtime" length="19" not-null="true" />
        </property>
        <property name="revcontent" type="java.lang.String">
            <column name="revcontent" length="65535" not-null="true" />
        </property>
        <property name="revstatus" type="int">
            <column name="revstatus" length="11" not-null="true" />
        </property>
    </class>
</hibernate-mapping>
